<?xml version="1.0" encoding="utf-8" standalone="yes"?>
<Parameters>
  <Connection>
    <DeviceParameters>/IF=tcpip /LOPO=11159 /SA=1</DeviceParameters>
    <ConnectionParameters>/RT=1000 /DAIP=127.0.0.1 /REPO=11160 /ANSL=1 /AM=* /PT=11169</ConnectionParameters>
  </Connection>
  <AsProject>
    <ApjFullFileName>C:\projects\PUA_Lab1_Baranek\PUA_Lab1_Baranek.apj</ApjFullFileName>
    <ProjectName>PUA_Lab1_Baranek</ProjectName>
    <ActiveConfigurationName>SIM_Config</ActiveConfigurationName>
    <LicenseDataFolder>C:\projects\PUA_Lab1_Baranek\Temp\Objects\SIM_Config\X20CP1586</LicenseDataFolder>
  </AsProject>
  <General>
    <DeleteParameterFile>false</DeleteParameterFile>
  </General>
</Parameters>